nectarstt/__init__.py
nectarstt/main.py
nectarstt/stt_engine.py
nectarstt/tts_engine.py
nectarstt/Main-Engine/Source/CodeScripts/Speech-To-TextEngine/speech-to-text.py
nectarstt/Main-Engine/Source/CodeScripts/Text-To-SpeechEngine/Offline/offline_text-to-speech.py
nectarstt/Main-Engine/Source/CodeScripts/Text-To-SpeechEngine/Online/Json_voice_organizer.py
nectarstt/Main-Engine/Source/CodeScripts/Text-To-SpeechEngine/Online/online_text_to_speech.py
nectarstt/Main-Engine/Source/Tests/test-1.py
nectarstt/Main-Engine/Source/Tests/test_2.py
nectarstt-0.1.2.dist-info/licenses/LICENSE
nectarstt-0.1.2.dist-info/METADATA
nectarstt-0.1.2.dist-info/WHEEL
nectarstt-0.1.2.dist-info/entry_points.txt
nectarstt-0.1.2.dist-info/top_level.txt
nectarstt-0.1.2.dist-info/RECORD
