Metadata-Version: 2.4
Name: nectarstt
Version: 0.1.2
Summary: Nectar Speech-to-Text And Text-to-Speech Engine
Author-email: Headlessripper <zashiron.inc@gmail.com>
License: <<<<<<< HEAD
Project-URL: Homepage, https://github.com/headlessripper/NectarSTT
Requires-Python: >=3.11
License-File: LICENSE
Requires-Dist: PyQt6
Requires-Dist: PyQt6-Qt6
Requires-Dist: PyQt6-sip
Requires-Dist: sounddevice
Requires-Dist: scipy
Requires-Dist: numpy
Requires-Dist: click
Dynamic: license-file
